pyciaaw/__init__.py
pyciaaw/__main__.py
pyciaaw/_ciaaw.cpython-313-x86_64-linux-gnu.so
pyciaaw/ciaaw
pyciaaw/ciaaw.h
pyciaaw/libciaaw.a
pyciaaw/libciaaw.so
pyciaaw.libs/libgfortran-3ec47101.so.5.0.0
pyciaaw.libs/libquadmath-67d31475.so.0.0.0
pyciaaw-1.2.0.dist-info/METADATA
pyciaaw-1.2.0.dist-info/WHEEL
pyciaaw-1.2.0.dist-info/entry_points.txt
pyciaaw-1.2.0.dist-info/top_level.txt
pyciaaw-1.2.0.dist-info/RECORD
pyciaaw-1.2.0.dist-info/licenses/LICENSE
pyciaaw-1.2.0.dist-info/sboms/auditwheel.cdx.json
