Metadata-Version: 2.4
Name: pyciaaw
Version: 1.2.0
Summary: pyciaaw: CIAAW for python.
Author-email: Milan Skocic <milan.skocic@gmail.com>
License-Expression: MIT
Project-URL: Documentation, https://milanskocic.github.io/ciaaw/index.html
Project-URL: Source, https://github.com/MilanSkocic/ciaaw
Classifier: Development Status :: 5 - Production/Stable
Classifier: Intended Audience :: Science/Research
Requires-Python: >=3.10
License-File: LICENSE
Dynamic: license-file
